jsonreference.py
jsonreference-2018.9.30.dist-info/LICENSE
jsonreference-2018.9.30.dist-info/METADATA
jsonreference-2018.9.30.dist-info/WHEEL
jsonreference-2018.9.30.dist-info/top_level.txt
jsonreference-2018.9.30.dist-info/RECORD
