Metadata-Version: 2.1
Name: jsonreference
Version: 2018.9.30
Summary: Dead simple way to access JSON data
Home-page: https://github.com/rajasimon/jsonreference
Author: Raja Simon
Author-email: rajasimon@icloud.com
License: UNKNOWN
Platform: UNKNOWN
Classifier: Programming Language :: Python :: 3.6
Classifier: Programming Language :: Python :: 3.7
